atomic/__init__.py
atomic/atoms.py
atomic/exceptions.py
atomic/logger_manager.py
atomic/particles.py
atomic/quarks.py
atomic/channels/__init__.py
atomic/channels/amqp.py
atomic/channels/channel.py
atomic/channels/configuration.py
atomic_py-1.0.2.dist-info/METADATA
atomic_py-1.0.2.dist-info/WHEEL
atomic_py-1.0.2.dist-info/top_level.txt
atomic_py-1.0.2.dist-info/RECORD
